uip/__init__.py
uip/main.py
uip/cliapis/__init__.py
uip/cliapis/apis.py
uip/cliconfig/__init__.py
uip/cliconfig/customformatter.py
uip/cliconfig/setupcli.py
uip/config/__init__.py
uip/config/config.py
uip/config/configoptions.py
uip/config/mergeconfig.py
uip/config/uip.yml
uip/config/verifyconfig.py
uip/constants/__init__.py
uip/constants/constants.py
uip/exceptions/__init__.py
uip/exceptions/customexceptions.py
uip/exceptions/errormessages.py
uip/parsecli/__init__.py
uip/parsecli/parsecli.py
uip/uipproject/__init__.py
uip/uipproject/uipproject.py
uip/uiptemplates/__init__.py
uip/uiptemplates/template.py
uip/uiptemplates/__pycache__/__init__.cpython-36.pyc
uip/uiptemplates/__pycache__/template.cpython-36.pyc
uip/uiptemplates/eventtemplates/ue-publisher/__init__.py
uip/uiptemplates/eventtemplates/ue-publisher/requirements.txt
uip/uiptemplates/eventtemplates/ue-publisher/template_config.yml
uip/uiptemplates/eventtemplates/ue-publisher/src/__init__.py
uip/uiptemplates/eventtemplates/ue-publisher/src/extension.py
uip/uiptemplates/eventtemplates/ue-publisher/src/extension.yml
uip/uiptemplates/eventtemplates/ue-publisher/src/templates/template.json
uip/uiptemplates/resources/setupscripts/__init__.py
uip/uiptemplates/resources/setupscripts/setup.cfg
uip/uiptemplates/resources/setupscripts/setup.py
uip/uiptemplates/tasktemplates/ue-task/__init__.py
uip/uiptemplates/tasktemplates/ue-task/requirements.txt
uip/uiptemplates/tasktemplates/ue-task/template_config.yml
uip/uiptemplates/tasktemplates/ue-task/src/__init__.py
uip/uiptemplates/tasktemplates/ue-task/src/extension.py
uip/uiptemplates/tasktemplates/ue-task/src/extension.yml
uip/uiptemplates/tasktemplates/ue-task/src/templates/template.json
uip/utils/__init__.py
uip/utils/custom_io.py
uip/utils/formatting.py
uip/utils/generic.py
uip_cli-2.0.1.dist-info/LICENSE.txt
uip_cli-2.0.1.dist-info/METADATA
uip_cli-2.0.1.dist-info/WHEEL
uip_cli-2.0.1.dist-info/entry_points.txt
uip_cli-2.0.1.dist-info/top_level.txt
uip_cli-2.0.1.dist-info/RECORD
