Metadata-Version: 2.1
Name: uip-cli
Version: 2.0.1
Summary: Universal Extension CLI for interfacing with Controller Web Services
Home-page: UNKNOWN
Author: Stonebranch
License: GNU General Public License
Platform: UNKNOWN
Classifier: Operating System :: POSIX :: Linux
Classifier: Operating System :: Microsoft :: Windows
Classifier: Programming Language :: Python :: 3
Requires-Python: >=3.6
Requires-Dist: jsonschema (>=3.2.0)
Requires-Dist: colorama (>=0.4.4)
Requires-Dist: requests (>=2.26.0)
Requires-Dist: jinja2 (>=2.11.3)
Requires-Dist: prettytable (>=1.0.1)
Requires-Dist: pyyaml (>=5.4.1)
Requires-Dist: setuptools (>=44.1.1)
Requires-Dist: wheel (>=0.37.1)
Provides-Extra: tests
Requires-Dist: configparser ; extra == 'tests'
Requires-Dist: mock ; extra == 'tests'
Requires-Dist: pyyaml ; extra == 'tests'
Requires-Dist: pytest ; extra == 'tests'
Requires-Dist: parameterized ; extra == 'tests'
Requires-Dist: pytest-cov ; extra == 'tests'
